{"commitInfo":{"timestamp":1748066589520,"operation":"STREAMING UPDATE","operationParameters":{"outputMode":"Append","queryId":"9e8ce0f9-c72a-4633-b804-a671fce6ed30","epochId":"198"},"readVersion":197,"isolationLevel":"Serializable","isBlindAppend":true,"operationMetrics":{"numRemovedFiles":"0","numOutputRows":"2","numOutputBytes":"4198","numAddedFiles":"1"},"engineInfo":"Apache-Spark/3.5.5 Delta-Lake/3.1.0","txnId":"8c98f6c8-6298-4f57-9f86-f83e815ee975"}}
{"txn":{"appId":"9e8ce0f9-c72a-4633-b804-a671fce6ed30","version":198,"lastUpdated":1748066589519}}
{"add":{"path":"part-00000-7ac703b3-22eb-446d-a272-1d6d638c61ce-c000.snappy.parquet","partitionValues":{},"size":4198,"modificationTime":1748066589509,"dataChange":true,"stats":"{\"numRecords\":2,\"minValues\":{\"time\":\"13:00\",\"month\":5,\"year\":2025,\"temperature\":25.3,\"feelslike\":28.1,\"wind\":16.6,\"direction\":\"N\",\"gust\":24.0,\"cloud\":100,\"humidity\":83,\"precipitation\":0.14,\"pressure\":1012.0,\"weather\":\"Overcast\",\"label\":\"Overcast\"},\"maxValues\":{\"time\":\"13:00\",\"month\":5,\"year\":2025,\"temperature\":25.3,\"feelslike\":28.1,\"wind\":16.6,\"direction\":\"N\",\"gust\":24.0,\"cloud\":100,\"humidity\":83,\"precipitation\":0.14,\"pressure\":1012.0,\"weather\":\"Overcast\",\"label\":\"Overcast\"},\"nullCount\":{\"time\":0,\"month\":0,\"year\":0,\"temperature\":0,\"feelslike\":0,\"wind\":0,\"direction\":0,\"gust\":0,\"cloud\":0,\"humidity\":0,\"precipitation\":0,\"pressure\":0,\"weather\":0,\"label\":0}}"}}
