{"commitInfo":{"timestamp":1748066503499,"operation":"STREAMING UPDATE","operationParameters":{"outputMode":"Append","queryId":"9e8ce0f9-c72a-4633-b804-a671fce6ed30","epochId":"170"},"readVersion":169,"isolationLevel":"Serializable","isBlindAppend":true,"operationMetrics":{"numRemovedFiles":"0","numOutputRows":"3","numOutputBytes":"4198","numAddedFiles":"1"},"engineInfo":"Apache-Spark/3.5.5 Delta-Lake/3.1.0","txnId":"c55d952b-1680-4124-979a-a9a41255879b"}}
{"txn":{"appId":"9e8ce0f9-c72a-4633-b804-a671fce6ed30","version":170,"lastUpdated":1748066503498}}
{"add":{"path":"part-00000-cdf412c8-3b05-495c-81cb-df3c4cebe604-c000.snappy.parquet","partitionValues":{},"size":4198,"modificationTime":1748066503488,"dataChange":true,"stats":"{\"numRecords\":3,\"minValues\":{\"time\":\"13:00\",\"month\":5,\"year\":2025,\"temperature\":25.3,\"feelslike\":28.1,\"wind\":16.6,\"direction\":\"N\",\"gust\":24.0,\"cloud\":100,\"humidity\":83,\"precipitation\":0.14,\"pressure\":1012.0,\"weather\":\"Overcast\",\"label\":\"Overcast\"},\"maxValues\":{\"time\":\"13:00\",\"month\":5,\"year\":2025,\"temperature\":25.3,\"feelslike\":28.1,\"wind\":16.6,\"direction\":\"N\",\"gust\":24.0,\"cloud\":100,\"humidity\":83,\"precipitation\":0.14,\"pressure\":1012.0,\"weather\":\"Overcast\",\"label\":\"Overcast\"},\"nullCount\":{\"time\":0,\"month\":0,\"year\":0,\"temperature\":0,\"feelslike\":0,\"wind\":0,\"direction\":0,\"gust\":0,\"cloud\":0,\"humidity\":0,\"precipitation\":0,\"pressure\":0,\"weather\":0,\"label\":0}}"}}
